ptterm/__init__.py
ptterm/key_mappings.py
ptterm/process.py
ptterm/screen.py
ptterm/stream.py
ptterm/terminal.py
ptterm/utils.py
ptterm/backends/__init__.py
ptterm/backends/base.py
ptterm/backends/darwin.py
ptterm/backends/posix.py
ptterm/backends/posix_utils.py
ptterm/backends/win32.py
ptterm/backends/win32_pipes.py
ptterm-0.2.dist-info/METADATA
ptterm-0.2.dist-info/RECORD
ptterm-0.2.dist-info/WHEEL
ptterm-0.2.dist-info/top_level.txt
